lib/__init__.py
lib/analyzers.py
lib/blockers.py
lib/data_providers.py
lib/nginx_log_parser.py
usr/share/xddos/cron
usr/share/xddos/disable.sh
usr/share/xddos/enable.sh
usr/share/xddos/logrotate.d.xddos
usr/share/xddos/runner.sh
usr/share/xddos/tlog.sh
xddos-1.1.16.data/scripts/xddos.py
xddos-1.1.16.dist-info/DESCRIPTION.rst
xddos-1.1.16.dist-info/entry_points.txt
xddos-1.1.16.dist-info/METADATA
xddos-1.1.16.dist-info/metadata.json
xddos-1.1.16.dist-info/RECORD
xddos-1.1.16.dist-info/top_level.txt
xddos-1.1.16.dist-info/WHEEL
xddos-1.1.16.dist-info/zip-safe
