Metadata-Version: 2.0
Name: xddos
Version: 1.1.16
Summary: XDDoS - DDoS protection system
Home-page: https://github.com/servancho/xddos
Author: Dmitry Shilyaev
Author-email: dima@justhost.ru
License: MIT
Keywords: d,d,o,s, ,p,r,o,t,e,c,t,i,o,n, ,n,g,i,n,x, ,w,e,b
Platform: UNKNOWN
Requires-Dist: argparse
